ssak/__init__.py
ssak/version.py
ssak/infer/__init__.py
ssak/infer/general.py
ssak/infer/kaldi_infer.py
ssak/infer/linstt_infer.py
ssak/infer/nemo_infer.py
ssak/infer/speechbrain_infer.py
ssak/infer/torchaudio_infer.py
ssak/infer/transformers_infer.py
ssak/infer/whisper_infer.py
ssak/infer/whisper_infer_v2.py
ssak/utils/__init__.py
ssak/utils/align.py
ssak/utils/align_transcriptions.py
ssak/utils/audio.py
ssak/utils/augment.py
ssak/utils/augment_reverberation.py
ssak/utils/curl.py
ssak/utils/dataset.py
ssak/utils/debug.py
ssak/utils/env.py
ssak/utils/format_diarization.py
ssak/utils/format_transcription.py
ssak/utils/gender.py
ssak/utils/kaldi.py
ssak/utils/kaldi_converter.py
ssak/utils/kaldi_dataset.py
ssak/utils/language.py
ssak/utils/linstt.py
ssak/utils/linstt_transcription_result.py
ssak/utils/misc.py
ssak/utils/monitoring.py
ssak/utils/nemo_dataset.py
ssak/utils/player.py
ssak/utils/scraping.py
ssak/utils/text.py
ssak/utils/text_ar.py
ssak/utils/text_basic.py
ssak/utils/text_latin.py
ssak/utils/text_ru.py
ssak/utils/text_utils.py
ssak/utils/train_utils.py
ssak/utils/transcriber.py
ssak/utils/tts.py
ssak/utils/vad.py
ssak/utils/viewer.py
ssak/utils/voice_conversion.py
ssak/utils/wer.py
ssak/utils/yaml_utils.py
ssak-0.0.2.dist-info/licenses/LICENSE
tools/__init__.py
tools/align_audio_transcript.py
tools/clean_text_ar.py
tools/clean_text_fr.py
tools/get_word_positions.py
tools/linstt_request.py
tools/linstt_streaming.py
tools/move_dataset.py
tools/play_segments.py
tools/total_duration.py
ssak-0.0.2.dist-info/METADATA
ssak-0.0.2.dist-info/WHEEL
ssak-0.0.2.dist-info/entry_points.txt
ssak-0.0.2.dist-info/top_level.txt
ssak-0.0.2.dist-info/RECORD
