Metadata-Version: 2.4
Name: ssak
Version: 0.0.2
Summary: Toolbox for Speech Processing.
Home-page: https://github.com/linagora-labs/ssak
Author: linto-ai
License: GPLv3
Requires-Python: >=3.9
License-File: LICENSE
Requires-Dist: numpy
Requires-Dist: typing_extensions
Requires-Dist: audiomentations
Requires-Dist: bitsandbytes
Requires-Dist: cyrtranslit
Requires-Dist: dtw-python
Requires-Dist: envsubst
Requires-Dist: googletrans>=3.1.0a0
Requires-Dist: jiwer>=3.0.5
Requires-Dist: langid
Requires-Dist: lang-trans
Requires-Dist: Levenshtein
Requires-Dist: librosa
Requires-Dist: matplotlib<=3.7.4
Requires-Dist: num2words
Requires-Dist: psutil
Requires-Dist: praat-textgrids
Requires-Dist: py3nvml
Requires-Dist: pyarabic
Requires-Dist: python-magic
Requires-Dist: python-slugify
Requires-Dist: so-vits-svc-fork
Requires-Dist: tensorboard
Requires-Dist: text2num
Requires-Dist: xmltodict
Requires-Dist: websockets
Dynamic: author
Dynamic: description
Dynamic: description-content-type
Dynamic: home-page
Dynamic: license
Dynamic: license-file
Dynamic: requires-dist
Dynamic: requires-python
Dynamic: summary
